odoo/addons/project_tag/README.rst
odoo/addons/project_tag/__init__.py
odoo/addons/project_tag/__manifest__.py
odoo/addons/project_tag/i18n/ca.po
odoo/addons/project_tag/i18n/es.po
odoo/addons/project_tag/i18n/he.po
odoo/addons/project_tag/i18n/it.po
odoo/addons/project_tag/i18n/project_tag.pot
odoo/addons/project_tag/models/__init__.py
odoo/addons/project_tag/models/project.py
odoo/addons/project_tag/readme/CONTRIBUTORS.rst
odoo/addons/project_tag/readme/DESCRIPTION.rst
odoo/addons/project_tag/readme/USAGE.rst
odoo/addons/project_tag/static/description/icon.png
odoo/addons/project_tag/static/description/index.html
odoo/addons/project_tag/views/project.xml
odoo13_addon_project_tag-13.0.1.0.1.dev13.dist-info/METADATA
odoo13_addon_project_tag-13.0.1.0.1.dev13.dist-info/WHEEL
odoo13_addon_project_tag-13.0.1.0.1.dev13.dist-info/top_level.txt
odoo13_addon_project_tag-13.0.1.0.1.dev13.dist-info/RECORD
